kubernetes_client/__init__.py
kubernetes_client/__version__.py
kubernetes_client/base.py
kubernetes_client/enums.py
kubernetes_client/kfserving.py
kubernetes_client/schema.py
kubernetes_client/utils.py
kubernetes_client-0.1.7.dist-info/METADATA
kubernetes_client-0.1.7.dist-info/WHEEL
kubernetes_client-0.1.7.dist-info/top_level.txt
kubernetes_client-0.1.7.dist-info/RECORD
